CHANGELOG.txt
LICENSE.txt
MANIFEST.in
README.txt
setup.py
numppy/__init__.py
numppy.egg-info/PKG-INFO
numppy.egg-info/SOURCES.txt
numppy.egg-info/dependency_links.txt
numppy.egg-info/top_level.txt